PopPUNK/__init__.py
PopPUNK/__main__.py
PopPUNK/bgmm.py
PopPUNK/dbscan.py
PopPUNK/mash.py
PopPUNK/models.py
PopPUNK/network.py
PopPUNK/plot.py
PopPUNK/prune_db.py
PopPUNK/refine.py
poppunk-0.1.0.dist-info/DESCRIPTION.rst
poppunk-0.1.0.dist-info/METADATA
poppunk-0.1.0.dist-info/RECORD
poppunk-0.1.0.dist-info/WHEEL
poppunk-0.1.0.dist-info/entry_points.txt
poppunk-0.1.0.dist-info/metadata.json
poppunk-0.1.0.dist-info/top_level.txt
