Metadata-Version: 2.0
Name: poppunk
Version: 0.1.0
Summary: PopPUNK (POPulation Partitioning Using Nucleotide Kmers)
Home-page: https://github.com/johnlees/PopPUNK
Author: John Lees and Nicholas Croucher
Author-email: john@johnlees.me
License: Apache Software License
Keywords: bacteria genomics population-genetics k-mer
Platform: UNKNOWN
Classifier: Development Status :: 4 - Beta
Classifier: Intended Audience :: Science/Research
Classifier: Topic :: Scientific/Engineering :: Bio-Informatics
Classifier: License :: OSI Approved :: Apache Software License
Classifier: Programming Language :: Python :: 3.6
Requires-Dist: DendroPy
Requires-Dist: hdbscan
Requires-Dist: matplotlib
Requires-Dist: networkx
Requires-Dist: numba
Requires-Dist: numpy
Requires-Dist: pandas
Requires-Dist: scikit-learn
Requires-Dist: scipy
Requires-Dist: sharedmem
Requires-Dist: statsmodels
